motor_odm/__init__.py
motor_odm/document.py
motor_odm/encoders.py
motor_odm/fixtures.py
motor_odm/helpers.py
motor_odm/query.py
tests/__init__.py
tests/conftest.py
tests/data.json
tests/test_db_commands.py
tests/test_helpers.py
tests/test_models.py
tests/test_query.py
Motor_ODM-0.1.dev0.dist-info/LICENSE
Motor_ODM-0.1.dev0.dist-info/METADATA
Motor_ODM-0.1.dev0.dist-info/WHEEL
Motor_ODM-0.1.dev0.dist-info/top_level.txt
Motor_ODM-0.1.dev0.dist-info/RECORD
