Metadata-Version: 2.1
Name: Motor-ODM
Version: 0.1.dev0
Summary: A MongoDB ODM based on Motor and Pydantic.
Home-page: https://github.com/Codello/Motor-ODM/
Author: Kim Wittenburg
Author-email: codello@wittenburg.kim
License: MIT
Keywords: MongoDB AsyncIO ODM Pydantic
Platform: any
Classifier: Development Status :: 3 - Alpha
Classifier: Intended Audience :: Developers
Classifier: License :: OSI Approved :: MIT License
Classifier: Operating System :: OS Independent
Classifier: Programming Language :: Python :: 3 :: Only
Classifier: Programming Language :: Python :: 3.7
Classifier: Programming Language :: Python :: 3.8
Classifier: Topic :: Database
Classifier: Topic :: Software Development :: Libraries :: Python Modules
Requires-Dist: PyMongo
Requires-Dist: Motor
Requires-Dist: Pydantic
Provides-Extra: dev
Requires-Dist: pytest ; extra == 'dev'
Requires-Dist: pytest-cov ; extra == 'dev'
Requires-Dist: pytest-asyncio ; extra == 'dev'
Requires-Dist: flake8 ; extra == 'dev'
Requires-Dist: isort ; extra == 'dev'
Requires-Dist: mypy ; extra == 'dev'
Requires-Dist: black ; extra == 'dev'
Requires-Dist: invoke ; extra == 'dev'
Provides-Extra: docs
Requires-Dist: setuptools-scm ; extra == 'docs'
Requires-Dist: sphinx-rtd-theme ; extra == 'docs'
Requires-Dist: sphinxcontrib-apidoc ; extra == 'docs'
Provides-Extra: typing
Requires-Dist: fastapi ; extra == 'typing'
